mnisiscom/MNI152_T1.nii
mnisiscom/OpenSans-Regular.ttf
mnisiscom/__init__.py
mnisiscom/brain_cmaps.py
mnisiscom/command_line.py
mnisiscom/mnisiscom.py
mnisiscom/siscom.py
mnisiscom/gui/android-chrome-192x192.png
mnisiscom/gui/android-chrome-512x512.png
mnisiscom/gui/favicon.ico
mnisiscom/gui/main.html
mnisiscom/gui/manifest.json
mnisiscom/gui/scripts.js
mnisiscom/gui/sliders.js
mnisiscom/gui/style.css
mnisiscom/gui/assets/css/argon.min.css
mnisiscom/gui/assets/css/bootstrap/bootstrap.min.css
mnisiscom/gui/assets/js/argon.min.js
mnisiscom/gui/assets/vendor/bootstrap/bootstrap.min.js
mnisiscom/gui/assets/vendor/font-awesome/css/font-awesome.min.css
mnisiscom/gui/assets/vendor/font-awesome/fonts/FontAwesome.otf
mnisiscom/gui/assets/vendor/font-awesome/fonts/fontawesome-webfont.eot
mnisiscom/gui/assets/vendor/font-awesome/fonts/fontawesome-webfont.svg
mnisiscom/gui/assets/vendor/font-awesome/fonts/fontawesome-webfont.ttf
mnisiscom/gui/assets/vendor/font-awesome/fonts/fontawesome-webfont.woff
mnisiscom/gui/assets/vendor/font-awesome/fonts/fontawesome-webfont.woff2
mnisiscom/gui/assets/vendor/jquery/jquery.min.js
mnisiscom/gui/assets/vendor/nouislider/js/nouislider.min.js
mnisiscom/gui/assets/vendor/popper/popper.js
mnisiscom/gui/assets/vendor/popper/popper.min.js
mnisiscom/gui/fonts/open-sans-v17-latin-300.woff
mnisiscom/gui/fonts/open-sans-v17-latin-300.woff2
mnisiscom/gui/fonts/open-sans-v17-latin-600.woff
mnisiscom/gui/fonts/open-sans-v17-latin-600.woff2
mnisiscom/gui/fonts/open-sans-v17-latin-700.woff
mnisiscom/gui/fonts/open-sans-v17-latin-700.woff2
mnisiscom/gui/fonts/open-sans-v17-latin-regular.woff
mnisiscom/gui/fonts/open-sans-v17-latin-regular.woff2
mnisiscom-0.4.0.dist-info/LICENSE.md
mnisiscom-0.4.0.dist-info/METADATA
mnisiscom-0.4.0.dist-info/WHEEL
mnisiscom-0.4.0.dist-info/entry_points.txt
mnisiscom-0.4.0.dist-info/top_level.txt
mnisiscom-0.4.0.dist-info/RECORD
