Metadata-Version: 2.1
Name: mnisiscom
Version: 0.4.0
Summary: A simple command line tool and GUI for computing subtraction ictal SPECT coregistered to MRI (SISCOM). mnisiscom is exclusively intended for research use!
Home-page: https://github.com/jeremymoreau/mnisiscom
Author: Jeremy Moreau
Author-email: jeremy.moreau@mail.mcgill.ca
License: MPL 2.0 and Healthcare Disclaimer
Keywords: neuroimaging spect mri siscom epilepsy radiology
Platform: UNKNOWN
Classifier: Intended Audience :: Science/Research
Classifier: License :: OSI Approved :: Mozilla Public License 2.0 (MPL 2.0)
Classifier: Programming Language :: Python
Classifier: Programming Language :: JavaScript
Classifier: Topic :: Scientific/Engineering :: Medical Science Apps.
Classifier: Topic :: Scientific/Engineering
Classifier: Operating System :: POSIX :: Linux
Classifier: Operating System :: MacOS
Classifier: Operating System :: Microsoft :: Windows
Classifier: Programming Language :: Python :: 3.5
Classifier: Programming Language :: Python :: 3.6
Classifier: Programming Language :: Python :: 3.7
Requires-Python: >=3.5, <3.8
Requires-Dist: numpy
Requires-Dist: nibabel
Requires-Dist: scikit-learn
Requires-Dist: nilearn
Requires-Dist: dipy
Requires-Dist: matplotlib
Requires-Dist: Pillow
Requires-Dist: click
Requires-Dist: colorama
Requires-Dist: eel
Requires-Dist: pywin32 ; platform_system == "Windows"
